Workbook

Sheet Panel
A1: Bynoesis · modelo economico v2
A2: Lo azul se edita; lo negro es formula. Cambia un supuesto aqui y se mueve todo el libro, incluida la curva de caja. Las cifras por plan vienen del analisis del 15/07/2026; las bajas, el CAC y el canal son supuestos sin medir y estan marcados como tales.
A5: Supuestos que decides tu
A6: Supuesto | B6: Valor | F6: De donde sale
A7: Mezcla de planes · Autonomo | B7: 0.55 | F7: Reparto de cuentas supuesto en el analisis del 15/07/2026.
A8: Mezcla de planes · Negocio | B8: 0.35 | F8: Las tres deben sumar 100 %.
A9: Mezcla de planes · Premium | B9: 0.1 | F9: Premium al 10 % es prudente: es el plan de menor margen.
A10: Bajas al mes (churn) | B10: 0.04 | F10: SUPUESTO SIN MEDIR. No hay clientes de pago que permitan medirlo.
A11: Coste de captar un cliente (CAC) | B11: 150 | F11: SUPUESTO SIN MEDIR. Figuraba en el modelo editable anterior.
A12: Gasto fijo mensual (opex) | B12: 3500 | F12: Constante del analisis del 15/07/2026.
A13: Altas al mes | B13: 10 | F13: Ritmo de captacion que quieres simular.
A14: Cuota de implantacion | B14: 99 | F14: Propuesta del 16/09/2026; se perdona en contratacion anual.
A15: Cuota de implantacion: % que la paga | B15: 1 | F15: Con 0 % el modelo se comporta como si no existiera.
A16: Caja inicial | B16: 0 | F16: Dinero disponible al empezar la simulacion.
A18: =IF(ABS($B$7+$B$8+$B$9-1)>0.0001,"AVISO: la mezcla de planes no suma 100 %","Mezcla correcta: suma 100 %")
A20: Lo que sale de ahi
A21: Resultado | B21: Valor | F21: Como se calcula
A22: Cuota media por cuenta (ARPU) | B22: =Unit_Economics!$B$12 | F22: Precio de cada plan por su peso en la mezcla.
A23: Contribucion media por cuenta | B23: =Unit_Economics!$D$12 | F23: Lo que deja cada cuenta al mes despues de servirla.
A24: Margen de contribucion | B24: =IF(Panel!$B$22=0,0,Panel!$B$23/Panel!$B$22) | F24: Contribucion sobre cuota media.
A25: Cuentas para cubrir el gasto fijo | B25: =IF(Panel!$B$23<=0,"-",ROUNDUP($B$12/Panel!$B$23,0)) | F25: Break-even: gasto fijo entre contribucion media.
A26: Vida media del cliente | B26: =IF($B$10<=0,"sin bajas",1/$B$10) | F26: Meses. Es 1 dividido entre las bajas mensuales.
A27: Valor de un cliente (LTV) | B27: =IF($B$10<=0,"-",Panel!$B$23/$B$10) | F27: Contribucion por vida media. No es facturacion: es lo que deja.
A28: LTV dividido entre CAC | B28: =IF(OR($B$11<=0,$B$10<=0),"-",Panel!$B$27/$B$11) | F28: Por debajo de 3 el negocio compra clientes demasiado caros.
A29: Meses para recuperar el CAC | B29: =IF(Panel!$B$23<=0,"-",$B$11/Panel!$B$23) | F29: Payback. Por encima de 12 la caja sufre aunque el LTV sea bueno.
A30: Mes en que la caja deja de bajar | B30: =Caja_36m!$B$6 | F30: Primer mes con resultado mensual positivo, segun Caja_36m.
A31: Caja minima que hace falta | B31: =Caja_36m!$B$7 | F31: El punto mas bajo de la curva: el dinero que hay que poder aguantar.
A33: Ninguna fila de bajas, CAC o comision es un dato observado: no hay todavia clientes de pago que permitan medirlos. El modelo sirve para ver que pasa si, no para afirmar que pasara. Primero tres a cinco clientes de pago y treinta dias de medicion.

Sheet Unit_Economics
A1: Economia por plan
A2: Precio, coste de software y contribucion son cifras verificadas del 15/07/2026. El bloque intermedio —soporte, onboarding, fijo por cuenta y comisiones— se calcula por diferencia: el analisis publica el total, no su desglose, y aqui no se inventa uno.
A5: Plan | B5: Precio | C5: Coste de software | D5: Contribucion | E5: Margen bruto | F5: Margen contribucion | G5: Soporte, onboarding y comisiones (por diferencia)
A6: Autonomo | B6: 29 | C6: 1.48 | D6: 20.83 | E6: =IF(B6=0,0,(B6-C6)/B6) | F6: =IF(B6=0,0,D6/B6) | G6: =B6-C6-D6
A7: Negocio | B7: 49 | C7: 3.04 | D7: 34.89 | E7: =IF(B7=0,0,(B7-C7)/B7) | F7: =IF(B7=0,0,D7/B7) | G7: =B7-C7-D7
A8: Premium | B8: 99 | C8: 18.47 | D8: 56.96 | E8: =IF(B8=0,0,(B8-C8)/B8) | F8: =IF(B8=0,0,D8/B8) | G8: =B8-C8-D8
A10: Mezcla y medias
A11: Concepto | B11: Cuota media | C11: Coste medio | D11: Contribucion media | G11: Peso de cada plan
A12: Media ponderada | B12: =B6*Panel!$B$7+B7*Panel!$B$8+B8*Panel!$B$9 | C12: =C6*Panel!$B$7+C7*Panel!$B$8+C8*Panel!$B$9 | D12: =D6*Panel!$B$7+D7*Panel!$B$8+D8*Panel!$B$9 | G12: =TEXT(Panel!$B$7,"0%")&" / "&TEXT(Panel!$B$8,"0%")&" / "&TEXT(Panel!$B$9,"0%")
A14: Plan | B14: Cobro anual | C14: Equivalente al mes | D14: Ahorro para el cliente | G14: Nota
A15: Autonomo | B15: 319 | C15: =B15/12 | D15: =29*12-B15 | G15: Cobra once meses y da doce. Mejora caja y reduce comisiones.
A16: Negocio | B16: 539 | C16: =B16/12 | D16: =49*12-B16 | G16: Cobra once meses y da doce. Mejora caja y reduce comisiones.
A17: Premium | B17: 1089 | C17: =B17/12 | D17: =99*12-B17 | G17: Cobra once meses y da doce. Mejora caja y reduce comisiones.
A19: El anual obliga a reservar capacidad de servicio durante doce meses, asi que su contribucion real depende del uso de voz y soporte que el piloto todavia no ha medido.

Sheet Vida_y_LTV
A1: Cuanto dura un cliente y cuanto deja
A2: Sin bajas no hay vida media y sin vida media no hay LTV: el modelo anterior describia un cliente que se queda para siempre. La fila resaltada es la que has puesto en el Panel.
A5: Bajas al mes | B5: Vida media (meses) | C5: LTV (contribucion) | D5: LTV / CAC | E5: Meses para recuperar el CAC | F5: Lectura
A6: 0.02 | B6: =1/A6 | C6: =Panel!$B$23/A6 | D6: =IF(Panel!$B$11<=0,"-",C6/Panel!$B$11) | E6: =IF(Panel!$B$23<=0,"-",Panel!$B$11/Panel!$B$23) | F6: =IF(D6="-","",IF(D6>=3,"Sostenible",IF(D6>=1,"Justo: el cliente apenas paga su captacion","Cada alta destruye valor")))
A7: 0.03 | B7: =1/A7 | C7: =Panel!$B$23/A7 | D7: =IF(Panel!$B$11<=0,"-",C7/Panel!$B$11) | E7: =IF(Panel!$B$23<=0,"-",Panel!$B$11/Panel!$B$23) | F7: =IF(D7="-","",IF(D7>=3,"Sostenible",IF(D7>=1,"Justo: el cliente apenas paga su captacion","Cada alta destruye valor")))
A8: 0.04 | B8: =1/A8 | C8: =Panel!$B$23/A8 | D8: =IF(Panel!$B$11<=0,"-",C8/Panel!$B$11) | E8: =IF(Panel!$B$23<=0,"-",Panel!$B$11/Panel!$B$23) | F8: =IF(D8="-","",IF(D8>=3,"Sostenible",IF(D8>=1,"Justo: el cliente apenas paga su captacion","Cada alta destruye valor")))
A9: 0.05 | B9: =1/A9 | C9: =Panel!$B$23/A9 | D9: =IF(Panel!$B$11<=0,"-",C9/Panel!$B$11) | E9: =IF(Panel!$B$23<=0,"-",Panel!$B$11/Panel!$B$23) | F9: =IF(D9="-","",IF(D9>=3,"Sostenible",IF(D9>=1,"Justo: el cliente apenas paga su captacion","Cada alta destruye valor")))
A10: 0.08 | B10: =1/A10 | C10: =Panel!$B$23/A10 | D10: =IF(Panel!$B$11<=0,"-",C10/Panel!$B$11) | E10: =IF(Panel!$B$23<=0,"-",Panel!$B$11/Panel!$B$23) | F10: =IF(D10="-","",IF(D10>=3,"Sostenible",IF(D10>=1,"Justo: el cliente apenas paga su captacion","Cada alta destruye valor")))
A11: 0.1 | B11: =1/A11 | C11: =Panel!$B$23/A11 | D11: =IF(Panel!$B$11<=0,"-",C11/Panel!$B$11) | E11: =IF(Panel!$B$23<=0,"-",Panel!$B$11/Panel!$B$23) | F11: =IF(D11="-","",IF(D11>=3,"Sostenible",IF(D11>=1,"Justo: el cliente apenas paga su captacion","Cada alta destruye valor")))
A13: Ninguna de estas filas es un dato. El CAC de 150 EUR aguanta bien salvo con bajas altas, pero tanto el CAC como las bajas son supuestos hasta que haya clientes de pago que permitan medirlos.

Sheet Canal_Comision
A1: Que cuesta cada forma de pagar al canal
A2: Las cinco estructuras evaluadas el 16/09/2026, recalculadas aqui con los supuestos del Panel. «Se lleva» es la parte de la contribucion total del cliente que acaba en el comercial: es la cifra que decide si el canal escala.
A5: Estructura | B5: Pago al alta | C5: % recurrente | D5: Meses de recurrente | E5: Coste total por cliente | F5: Se lleva (% contribucion) | G5: Recupera en (meses) · Gana a las altas del Panel en el mes 12
A6: A · una mensualidad al alta | B6: =Panel!$B$22 | C6: 0 | D6: 0 | E6: =B6+C6*Panel!$B$22*MIN(D6,Panel!$B$26) | F6: =IF(Panel!$B$23*Panel!$B$26=0,0,E6/(Panel!$B$23*Panel!$B$26)) | G6: =IF(Panel!$B$23<=0,"-",TEXT(E6/Panel!$B$23,"0.0")&" meses · "&TEXT((Panel!$B$23*12-E6)*Panel!$B$13,"#,##0 €"))
A7: B · dos mensualidades al alta | B7: =Panel!$B$22*2 | C7: 0 | D7: 0 | E7: =B7+C7*Panel!$B$22*MIN(D7,Panel!$B$26) | F7: =IF(Panel!$B$23*Panel!$B$26=0,0,E7/(Panel!$B$23*Panel!$B$26)) | G7: =IF(Panel!$B$23<=0,"-",TEXT(E7/Panel!$B$23,"0.0")&" meses · "&TEXT((Panel!$B$23*12-E7)*Panel!$B$13,"#,##0 €"))
A8: C · 20 % recurrente de por vida | B8: 0 | C8: 0.2 | D8: 999 | E8: =B8+C8*Panel!$B$22*MIN(D8,Panel!$B$26) | F8: =IF(Panel!$B$23*Panel!$B$26=0,0,E8/(Panel!$B$23*Panel!$B$26)) | G8: =IF(Panel!$B$23<=0,"-",TEXT(E8/Panel!$B$23,"0.0")&" meses · "&TEXT((Panel!$B$23*12-E8)*Panel!$B$13,"#,##0 €"))
A9: D · 1 mes + 10 % durante 12 meses | B9: =Panel!$B$22 | C9: 0.1 | D9: 12 | E9: =B9+C9*Panel!$B$22*MIN(D9,Panel!$B$26) | F9: =IF(Panel!$B$23*Panel!$B$26=0,0,E9/(Panel!$B$23*Panel!$B$26)) | G9: =IF(Panel!$B$23<=0,"-",TEXT(E9/Panel!$B$23,"0.0")&" meses · "&TEXT((Panel!$B$23*12-E9)*Panel!$B$13,"#,##0 €"))
A10: E · 2 meses + 5 % durante 12 meses | B10: =Panel!$B$22*2 | C10: 0.05 | D10: 12 | E10: =B10+C10*Panel!$B$22*MIN(D10,Panel!$B$26) | F10: =IF(Panel!$B$23*Panel!$B$26=0,0,E10/(Panel!$B$23*Panel!$B$26)) | G10: =IF(Panel!$B$23<=0,"-",TEXT(E10/Panel!$B$23,"0.0")&" meses · "&TEXT((Panel!$B$23*12-E10)*Panel!$B$13,"#,##0 €"))
A12: La C es la mas cara por cliente y la mas atractiva para el comercial; la A es la mas barata y la que peor alinea, porque cobra igual si el cliente dura un mes que si dura tres anos. La D paga pronto, mantiene el coste de canal contenido y premia la permanencia: es la propuesta.
A15: Por que un comercial a sueldo no sale
A16: Concepto | B16: Valor | G16: Lectura
A17: Coste cargado de un comercial | B17: 2400 | G17: Sueldo, seguridad social y estructura.
A18: Comision recurrente que cobraria | B18: 0.2 | G18: Sobre la cuota, no sobre la contribucion.
A19: Cuentas activas suyas para cubrirse | B19: =IF(Panel!$B$22*$B$18<=0,"-",ROUNDUP($B$17/(Panel!$B$22*$B$18),0)) | G19: ="A las altas del Panel, tardaria "&TEXT(B19/MAX(Panel!$B$13,1),"0.0")&" meses en llegar."
A21: La conclusion no es «vende mas»: con esta cuota media, el canal tiene que ser comision pura, a tiempo parcial o por prescriptor. Una nomina exige una cartera propia que tarda anos en construirse.

Sheet Implantacion
A1: La cuota de implantacion y la caja del alta
A2: Una cuota al alta convierte la captacion en caja neutra o positiva. Con cero clientes y sin inversor, esa es la diferencia entre poder pagar a diez comerciales y no poder pagar a uno.
A5: Concepto | B5: Sin cuota | C5: Con la cuota del Panel | F5: Nota
A6: Primera cuota del cliente | B6: =Panel!$B$22 | C6: =Panel!$B$22 | F6: La mensualidad del mes en que firma.
A7: Cuota de implantacion cobrada | B7: 0 | C7: =Panel!$B$14*Panel!$B$15 | F7: Se perdona en contratacion anual, de ahi el porcentaje del Panel.
A8: Comision pagada al firmar (estructura D) | B8: =-Panel!$B$22 | C8: =-Panel!$B$22 | F8: La estructura D paga una mensualidad al alta.
A9: Caja neta el mes de la firma | B9: =SUM(B6:B8) | C9: =SUM(C6:C8) | F9: Positivo significa que captar no consume caja ese mes.
A10: A las altas del Panel, al mes | B10: =B9*Panel!$B$13 | C10: =C9*Panel!$B$13 | F10: Lo que entra o sale de caja cada mes solo por captar.
A12: Compromiso pendiente por ese cliente (10 % x 12 meses) | B12: =-0.1*Panel!$B$22*12 | C12: =-0.1*Panel!$B$22*12 | F12: No sale de caja al firmar, pero esta comprometido.
A13: Coste total del canal por cliente | B13: =Canal_Comision!$E$9 | C13: =Canal_Comision!$E$9 | F13: Alta mas recurrente, tal como lo calcula la hoja Canal_Comision.
A15: El analisis del 16/09/2026 cifraba en «unos 53 EUR» la caja neta de la firma comparando la cuota con la comision de alta (99 - 43). Aqui se desglosa el calculo completo, incluida la primera mensualidad y el compromiso recurrente, para que se vea de donde sale cada euro. Es coherente con lo que el modelo ya reconoce: el onboarding consume entre 30 y 120 minutos de founder que hoy se regalan. La cuota pone precio a ese trabajo en vez de esconderlo en el margen.

Sheet Caja_36m
A1: Caja mes a mes, 36 meses
A2: El break-even en numero de cuentas no dice cuantos meses cuesta llegar ni cuanto dinero hay que poner por el camino, que es la pregunta que de verdad limita. Cada mes entran las altas del Panel y se van las bajas; la comision es la estructura D.
A5: Resumen
A6: Mes en que el resultado mensual se vuelve positivo | B6: =IFERROR(INDEX($A$12:$A$47,MATCH(TRUE,INDEX($H$12:$H$47>0,0),0)),"no llega en 36 meses")
A7: Caja minima (el punto mas bajo de la curva) | B7: =MIN($I$12:$I$47)
A8: Cuentas activas al mes 36 | B8: =$C$47
A9: Caja acumulada al mes 36 | B9: =$I$47
A11: Mes | B11: Altas | C11: Cuentas activas | D11: Ingreso (MRR) | E11: Contribucion | F11: Comision del canal | G11: Implantacion cobrada | H11: Resultado del mes | I11: Caja acumulada
A12: 1 | B12: =Panel!$B$13 | C12: =B12 | D12: =C12*Panel!$B$22 | E12: =C12*Panel!$B$23 | F12: =-(B12*Panel!$B$22+0.1*Panel!$B$22*MIN(C12,SUM(B12:B12))) | G12: =B12*Panel!$B$14*Panel!$B$15 | H12: =E12+F12+G12-Panel!$B$12 | I12: =Panel!$B$16+H12
A13: 2 | B13: =Panel!$B$13 | C13: =C12*(1-Panel!$B$10)+B13 | D13: =C13*Panel!$B$22 | E13: =C13*Panel!$B$23 | F13: =-(B13*Panel!$B$22+0.1*Panel!$B$22*MIN(C13,SUM(B13:B13))) | G13: =B13*Panel!$B$14*Panel!$B$15 | H13: =E13+F13+G13-Panel!$B$12 | I13: =I12+H13
A14: 3 | B14: =Panel!$B$13 | C14: =C13*(1-Panel!$B$10)+B14 | D14: =C14*Panel!$B$22 | E14: =C14*Panel!$B$23 | F14: =-(B14*Panel!$B$22+0.1*Panel!$B$22*MIN(C14,SUM(B14:B14))) | G14: =B14*Panel!$B$14*Panel!$B$15 | H14: =E14+F14+G14-Panel!$B$12 | I14: =I13+H14
A15: 4 | B15: =Panel!$B$13 | C15: =C14*(1-Panel!$B$10)+B15 | D15: =C15*Panel!$B$22 | E15: =C15*Panel!$B$23 | F15: =-(B15*Panel!$B$22+0.1*Panel!$B$22*MIN(C15,SUM(B15:B15))) | G15: =B15*Panel!$B$14*Panel!$B$15 | H15: =E15+F15+G15-Panel!$B$12 | I15: =I14+H15
A16: 5 | B16: =Panel!$B$13 | C16: =C15*(1-Panel!$B$10)+B16 | D16: =C16*Panel!$B$22 | E16: =C16*Panel!$B$23 | F16: =-(B16*Panel!$B$22+0.1*Panel!$B$22*MIN(C16,SUM(B16:B16))) | G16: =B16*Panel!$B$14*Panel!$B$15 | H16: =E16+F16+G16-Panel!$B$12 | I16: =I15+H16
A17: 6 | B17: =Panel!$B$13 | C17: =C16*(1-Panel!$B$10)+B17 | D17: =C17*Panel!$B$22 | E17: =C17*Panel!$B$23 | F17: =-(B17*Panel!$B$22+0.1*Panel!$B$22*MIN(C17,SUM(B17:B17))) | G17: =B17*Panel!$B$14*Panel!$B$15 | H17: =E17+F17+G17-Panel!$B$12 | I17: =I16+H17
A18: 7 | B18: =Panel!$B$13 | C18: =C17*(1-Panel!$B$10)+B18 | D18: =C18*Panel!$B$22 | E18: =C18*Panel!$B$23 | F18: =-(B18*Panel!$B$22+0.1*Panel!$B$22*MIN(C18,SUM(B18:B18))) | G18: =B18*Panel!$B$14*Panel!$B$15 | H18: =E18+F18+G18-Panel!$B$12 | I18: =I17+H18
A19: 8 | B19: =Panel!$B$13 | C19: =C18*(1-Panel!$B$10)+B19 | D19: =C19*Panel!$B$22 | E19: =C19*Panel!$B$23 | F19: =-(B19*Panel!$B$22+0.1*Panel!$B$22*MIN(C19,SUM(B19:B19))) | G19: =B19*Panel!$B$14*Panel!$B$15 | H19: =E19+F19+G19-Panel!$B$12 | I19: =I18+H19
A20: 9 | B20: =Panel!$B$13 | C20: =C19*(1-Panel!$B$10)+B20 | D20: =C20*Panel!$B$22 | E20: =C20*Panel!$B$23 | F20: =-(B20*Panel!$B$22+0.1*Panel!$B$22*MIN(C20,SUM(B20:B20))) | G20: =B20*Panel!$B$14*Panel!$B$15 | H20: =E20+F20+G20-Panel!$B$12 | I20: =I19+H20
A21: 10 | B21: =Panel!$B$13 | C21: =C20*(1-Panel!$B$10)+B21 | D21: =C21*Panel!$B$22 | E21: =C21*Panel!$B$23 | F21: =-(B21*Panel!$B$22+0.1*Panel!$B$22*MIN(C21,SUM(B21:B21))) | G21: =B21*Panel!$B$14*Panel!$B$15 | H21: =E21+F21+G21-Panel!$B$12 | I21: =I20+H21
A22: 11 | B22: =Panel!$B$13 | C22: =C21*(1-Panel!$B$10)+B22 | D22: =C22*Panel!$B$22 | E22: =C22*Panel!$B$23 | F22: =-(B22*Panel!$B$22+0.1*Panel!$B$22*MIN(C22,SUM(B22:B22))) | G22: =B22*Panel!$B$14*Panel!$B$15 | H22: =E22+F22+G22-Panel!$B$12 | I22: =I21+H22
A23: 12 | B23: =Panel!$B$13 | C23: =C22*(1-Panel!$B$10)+B23 | D23: =C23*Panel!$B$22 | E23: =C23*Panel!$B$23 | F23: =-(B23*Panel!$B$22+0.1*Panel!$B$22*MIN(C23,SUM(B23:B23))) | G23: =B23*Panel!$B$14*Panel!$B$15 | H23: =E23+F23+G23-Panel!$B$12 | I23: =I22+H23
A24: 13 | B24: =Panel!$B$13 | C24: =C23*(1-Panel!$B$10)+B24 | D24: =C24*Panel!$B$22 | E24: =C24*Panel!$B$23 | F24: =-(B24*Panel!$B$22+0.1*Panel!$B$22*MIN(C24,SUM(B24:B24))) | G24: =B24*Panel!$B$14*Panel!$B$15 | H24: =E24+F24+G24-Panel!$B$12 | I24: =I23+H24
... A47: 36 | B47: =Panel!$B$13 | C47: =C46*(1-Panel!$B$10)+B47 | D47: =C47*Panel!$B$22 | E47: =C47*Panel!$B$23 | F47: =-(B47*Panel!$B$22+0.1*Panel!$B$22*MIN(C47,SUM(B47:B47))) | G47: =B47*Panel!$B$14*Panel!$B$15 | H47: =E47+F47+G47-Panel!$B$12 | I47: =I46+H47
A49: La curva supone que las altas del Panel se mantienen constantes y que las bajas se aplican a la cartera existente antes de sumar las nuevas. No incluye IVA, impuestos ni inversiones: mide si el negocio se paga a si mismo.

Sheet Fuentes_y_pendientes
A1: De donde sale cada numero y que falta por medir
A2: Un modelo economico sin trazabilidad es una opinion con decimales. Aqui esta el origen de cada cifra y, sobre todo, lo que todavia no es un dato.
A5: Cifra | B5: Valor | C5: Estado | D5: Origen
A6: Precios 29 / 49 / 99 EUR | B6: Adoptado | C6: Decidido | D6: Decisiones: «Precio adoptado, prueba completa y despues modo consulta» (15/07/2026). Coincide con el catalogo del codigo.
A7: Coste de software por plan | B7: 1,48 / 3,04 / 18,47 | C7: Calculado | D7: Unit-economics-y-cerebro-interno.md (15/07/2026): Stripe, WhatsApp, IA, transcripcion, extraccion, almacenamiento y voz.
A8: Contribucion por plan | B8: 20,83 / 34,89 / 56,96 | C8: Calculado | D8: Mismo analisis. Ya descuenta soporte, onboarding y fijo por cuenta.
A9: Mezcla 55 / 35 / 10 | B9: Supuesto | C9: SIN MEDIR | D9: Reparto de planes asumido. Cambiara con el piloto.
A10: Bajas mensuales | B10: 4 % | C10: SIN MEDIR | D10: No hay clientes de pago. Cualquier LTV calculado sobre esto es una hipotesis, no una promesa.
A11: CAC 150 EUR | B11: Supuesto | C11: SIN MEDIR | D11: Figuraba en el modelo editable anterior; no hay campanas medidas.
A12: Opex 3.500 EUR | B12: Constante | C12: Supuesto | D12: Analisis del 15/07/2026. Asume que vende el founder.
A13: Estructuras de comision | B13: A a E | C13: Propuesta | D13: Canal-comercial-y-comisiones.md (16/09/2026). Nada aprobado: el founder reserva descuento, porcentaje, duracion y devoluciones.
A14: Cuota de implantacion 99 EUR | B14: Propuesta | C14: Sin aprobar | D14: Misma fuente. Perdonada en contratacion anual.
A15: Coste cargado de comercial | B15: 2.400 EUR | C15: Supuesto | D15: Sueldo mas seguridad social y estructura.
A17: Antes de firmar con nadie: tres a cinco clientes de pago y treinta dias midiendo bajas, soporte por cuenta y coste real de captacion. Con eso, este libro deja de ser un escenario y pasa a ser un modelo.
