Workbook

Sheet Resumen
A1: Noesis — Modelo economico
A2: Modelo vivo: las celdas azules son entradas editables y el resto son formulas. Las cifras proceden del analisis interno fechado el 15/07/2026 con fuentes citadas en la hoja Fuentes. Lo que el repositorio no acredita esta en la hoja Datos_Pendientes y NO se ha estimado.
A4: Catalogo adoptado
A5: Concepto | B5: Autonomo | C5: Negocio | D5: Premium | E5: Unidad | F5: Nota
A6: Precio mensual | B6: ='Supuestos'!B7 | C6: ='Supuestos'!C7 | D6: ='Supuestos'!D7 | E6: €/mes + IVA | F6: Catalogo adoptado tras el analisis
A7: Precio anual | B7: 319 | C7: 539 | D7: 1089 | E7: €/ano + IVA | F7: Cobra 11 meses, da acceso 12
A8: Mix de clientes supuesto | B8: ='Supuestos'!B8 | C8: ='Supuestos'!C8 | D8: ='Supuestos'!D8 | E8: % | F8: Hipotesis de escala, a recalibrar
A10: Resultado por plan (modelo Noesis)
A11: Metrica | B11: Autonomo | C11: Negocio | D11: Premium | E11: Unidad | F11: Nota
A12: COGS software | B12: ='Unit_Economics'!E13 | C12: ='Unit_Economics'!F13 | D12: ='Unit_Economics'!G13 | E12: €/mes | F12: Stripe, WhatsApp, IA, voz, almacenamiento
A13: Margen bruto | B13: ='Unit_Economics'!E14 | C13: ='Unit_Economics'!F14 | D13: ='Unit_Economics'!G14 | E13: % | F13: Sobre precio neto
A14: Contribucion | B14: ='Unit_Economics'!E18 | C14: ='Unit_Economics'!F18 | D14: ='Unit_Economics'!G18 | E14: €/mes | F14: Ya descuenta soporte, onboarding y fijo
A15: Margen de contribucion | B15: ='Unit_Economics'!E19 | C15: ='Unit_Economics'!F19 | D15: ='Unit_Economics'!G19 | E15: % | F15: Sin CAC
A17: Punto de equilibrio
A18: Metrica | B18: Valor | E18: Unidad | F18: Nota
A19: Contribucion media ponderada | B19: =Unit_Economics!E18*Supuestos!B8+Unit_Economics!F18*Supuestos!C8+Unit_Economics!G18*Supuestos!D8 | E19: €/cuenta/mes | F19: Segun el mix de la hoja Supuestos
A20: Opex fijo mensual | B20: =Supuestos!B41 | E20: €/mes | F20: HIPOTESIS: 3.500 €. Sustituir por el gasto real
A21: Cuentas para equilibrio | B21: =IF(B19>0,ROUNDUP(B20/B19,0),"") | E21: cuentas | F21: Con el opex real este numero cambia
A22: Ingreso mensual en equilibrio | B22: =IF(B21<>"",B21*(Supuestos!B7*Supuestos!B8+Supuestos!C7*Supuestos!C8+Supuestos!D7*Supuestos!D8),"") | E22: €/mes | F22: Sin IVA
A24: Aviso
A25: Ninguna cifra de este libro es un resultado observado. Son supuestos de planificacion fechados que el piloto debe recalibrar. El opex fijo, los sueldos, el reparto societario y el CAC no constan en el repositorio: estan en Datos_Pendientes sin rellenar.

Sheet Supuestos
A1: Supuestos
A2: Celdas azules = entradas editables. Cambiar aqui recalcula todo el libro. Cada driver lleva fecha y fuente; los marcados como Supuesto no estan verificados.
A4: Supuestos por plan
A5: Driver | B5: Autonomo | C5: Negocio | D5: Premium | E5: Unidad | F5: Fuente / criterio
A6: Precio actual | B6: 29 | C6: 39 | D6: 79 | E6: €/mes + IVA | F6: Catalogo anterior
A7: Precio adoptado | B7: 29 | C7: 49 | D7: 99 | E7: €/mes + IVA | F7: Recomendacion de unit economics
A8: Mix de clientes | B8: 0.55 | C8: 0.35 | D8: 0.1 | E8: % | F8: Supuesto de escala
A9: Creditos avanzados incluidos | B9: 75 | C9: 300 | D9: 1500 | E9: acciones/mes | F9: Catalogo actual
A10: Uso esperado del limite | B10: 0.35 | C10: 0.4 | D10: 0.25 | E10: % | F10: Supuesto conservador
A11: Resolucion por cerebro interno | B11: 0.6 | C11: 0.6 | D11: 0.6 | E11: % | F11: Objetivo tras piloto
A12: WhatsApp utility enviados | B12: 30 | C12: 80 | D12: 200 | E12: mensajes/mes | F12: Supuesto operativo
A13: WhatsApp service recibidos | B13: 100 | C13: 300 | D13: 1000 | E13: mensajes/mes | F13: Gratis hoy; sensibilidad futura
A14: Audio transcrito | B14: 15 | C14: 60 | D14: 200 | E14: min/mes | F14: Supuesto operativo
A15: Documentos procesados | B15: 15 | C15: 50 | D15: 200 | E15: docs/mes | F15: Supuesto operativo
A16: Documentos que escalan fuera | B16: 0.2 | C16: 0.2 | D16: 0.2 | E16: % | F16: OCR local primero
A17: Almacenamiento | B17: 0.25 | C17: 1 | D17: 3 | E17: GB/cuenta | F17: Supuesto operativo
... A20: Onboarding inicial | B20: 30 | C20: 60 | D20: 120 | E20: min/cuenta | F20: Amortizado en 12 meses
A23: Supuestos globales
A24: Driver | B24: Valor | C24: Unidad | D24: Fecha | E24: Fuente | F24: Nota
A25: EUR por USD | B25: 0.87680842 | C25: EUR/USD | D25: 14/07/2026 | E25: ECB | F25: 1 EUR = 1,1405 USD
A26: Stripe Payments | B26: 0.015 | C26: % ingreso | D26: 15/07/2026 | E26: Stripe | F26: Tarjeta EEE estandar
A27: Stripe Billing | B27: 0.007 | C27: % ingreso | D27: 15/07/2026 | E27: Stripe | F27: Pago por uso
A28: Stripe fijo | B28: 0.25 | C28: €/transaccion | D28: 15/07/2026 | E28: Stripe | F28: Una renovacion mensual
A29: WhatsApp utility Espana | B29: 0.0166 | C29: €/mensaje | D29: 15/07/2026 | E29: Meta / rate card | F29: Mensaje entregado
A30: WhatsApp service futuro | B30: 0.0166 | C30: €/mensaje | D30: 15/07/2026 | E30: Sensibilidad | F30: Actualmente 0 €
A31: Haiku 4.5 por interaccion | B31: 0.014 | C31: USD/interaccion | D31: 15/07/2026 | E31: Anthropic | F31: 8k input + 1,2k output
A32: Qwen3 32B por interaccion | B32: 0.003028 | C32: USD/interaccion | D32: 15/07/2026 | E32: Groq | F32: Mismo supuesto de tokens
A33: Peso Qwen en fallback | B33: 0.8 | C33: % | D33: 15/07/2026 | E33: Arquitectura hibrida | F33: Resto Haiku
A34: Whisper Turbo | B34: 0.04 | C34: USD/hora | D34: 15/07/2026 | E34: Groq | F34: Solo transcripcion
A35: Extraccion externa documento | B35: 0.012 | C35: €/documento | D35: 15/07/2026 | E35: Supuesto | F35: Validar con corpus real
A36: Object storage | B36: 0.015 | C36: USD/GB-mes | D36: 15/07/2026 | E36: Railway | F36: Sin egress
... A44: Cuentas para repartir fijo | B44: 100 | C44: cuentas | D44: 15/07/2026 | E44: Escenario base | F44: Solo unit economics por plan

Sheet Unit_Economics
A1: Unit economics por plan
A2: Escenario base hibrido: cerebro interno resuelve el 60%; del resto, 80% Qwen y 20% Haiku. Columnas B-D = catalogo anterior (29/39/79). Columnas E-G = catalogo adoptado (29/49/99).
A4: Metrica | B4: Autonomo ant. | C4: Negocio ant. | D4: Premium ant. | E4: Autonomo adop. | F4: Negocio adop. | G4: Premium adop. | H4: Unidad
A5: Precio neto | B5: ='Supuestos'!B$6 | C5: ='Supuestos'!C$6 | D5: ='Supuestos'!D$6 | E5: ='Supuestos'!B$7 | F5: ='Supuestos'!C$7 | G5: ='Supuestos'!D$7 | H5: €/mes
A6: Stripe | B6: =B5*('Supuestos'!$B$26+'Supuestos'!$B$27)+'Supuestos'!$B$28 | C6: =C5*('Supuestos'!$B$26+'Supuestos'!$B$27)+'Supuestos'!$B$28 | D6: =D5*('Supuestos'!$B$26+'Supuestos'!$B$27)+'Supuestos'!$B$28 | E6: =E5*('Supuestos'!$B$26+'Supuestos'!$B$27)+'Supuestos'!$B$28 | F6: =F5*('Supuestos'!$B$26+'Supuestos'!$B$27)+'Supuestos'!$B$28 | G6: =G5*('Supuestos'!$B$26+'Supuestos'!$B$27)+'Supuestos'!$B$28 | H6: €/mes
A7: WhatsApp utility | B7: ='Supuestos'!B$12*'Supuestos'!$B$29 | C7: ='Supuestos'!C$12*'Supuestos'!$B$29 | D7: ='Supuestos'!D$12*'Supuestos'!$B$29 | E7: ='Supuestos'!B$12*'Supuestos'!$B$29 | F7: ='Supuestos'!C$12*'Supuestos'!$B$29 | G7: ='Supuestos'!D$12*'Supuestos'!$B$29 | H7: €/mes
A8: IA avanzada | B8: ='Supuestos'!B$9*'Supuestos'!B$10*(1-'Supuestos'!B$11)*('Supuestos'!$B$33*'Supuestos'!$B$32+(1-'Supuestos'!$B$33)*'Supuestos'!$B$31)*'Supuestos'!$B$25 | C8: ='Supuestos'!C$9*'Supuestos'!C$10*(1-'Supuestos'!C$11)*('Supuestos'!$B$33*'Supuestos'!$B$32+(1-'Supuestos'!$B$33)*'Supuestos'!$B$31)*'Supuestos'!$B$25 | D8: ='Supuestos'!D$9*'Supuestos'!D$10*(1-'Supuestos'!D$11)*('Supuestos'!$B$33*'Supuestos'!$B$32+(1-'Supuestos'!$B$33)*'Supuestos'!$B$31)*'Supuestos'!$B$25 | E8: ='Supuestos'!B$9*'Supuestos'!B$10*(1-'Supuestos'!B$11)*('Supuestos'!$B$33*'Supuestos'!$B$32+(1-'Supuestos'!$B$33)*'Supuestos'!$B$31)*'Supuestos'!$B$25 | F8: ='Supuestos'!C$9*'Supuestos'!C$10*(1-'Supuestos'!C$11)*('Supuestos'!$B$33*'Supuestos'!$B$32+(1-'Supuestos'!$B$33)*'Supuestos'!$B$31)*'Supuestos'!$B$25 | G8: ='Supuestos'!D$9*'Supuestos'!D$10*(1-'Supuestos'!D$11)*('Supuestos'!$B$33*'Supuestos'!$B$32+(1-'Supuestos'!$B$33)*'Supuestos'!$B$31)*'Supuestos'!$B$25 | H8: €/mes
A9: Transcripcion | B9: ='Supuestos'!B$14/60*'Supuestos'!$B$34*'Supuestos'!$B$25 | C9: ='Supuestos'!C$14/60*'Supuestos'!$B$34*'Supuestos'!$B$25 | D9: ='Supuestos'!D$14/60*'Supuestos'!$B$34*'Supuestos'!$B$25 | E9: ='Supuestos'!B$14/60*'Supuestos'!$B$34*'Supuestos'!$B$25 | F9: ='Supuestos'!C$14/60*'Supuestos'!$B$34*'Supuestos'!$B$25 | G9: ='Supuestos'!D$14/60*'Supuestos'!$B$34*'Supuestos'!$B$25 | H9: €/mes
A10: Extraccion externa | B10: ='Supuestos'!B$15*'Supuestos'!B$16*'Supuestos'!$B$35 | C10: ='Supuestos'!C$15*'Supuestos'!C$16*'Supuestos'!$B$35 | D10: ='Supuestos'!D$15*'Supuestos'!D$16*'Supuestos'!$B$35 | E10: ='Supuestos'!B$15*'Supuestos'!B$16*'Supuestos'!$B$35 | F10: ='Supuestos'!C$15*'Supuestos'!C$16*'Supuestos'!$B$35 | G10: ='Supuestos'!D$15*'Supuestos'!D$16*'Supuestos'!$B$35 | H10: €/mes
A11: Almacenamiento | B11: ='Supuestos'!B$17*'Supuestos'!$B$36*'Supuestos'!$B$25 | C11: ='Supuestos'!C$17*'Supuestos'!$B$36*'Supuestos'!$B$25 | D11: ='Supuestos'!D$17*'Supuestos'!$B$36*'Supuestos'!$B$25 | E11: ='Supuestos'!B$17*'Supuestos'!$B$36*'Supuestos'!$B$25 | F11: ='Supuestos'!C$17*'Supuestos'!$B$36*'Supuestos'!$B$25 | G11: ='Supuestos'!D$17*'Supuestos'!$B$36*'Supuestos'!$B$25 | H11: €/mes
A12: Voz Premium | B12: =IF('Supuestos'!B$18>0,'Supuestos'!B$18*'Supuestos'!$B$37*'Supuestos'!$B$25+'Supuestos'!$B$38*'Supuestos'!$B$25,0) | C12: =IF('Supuestos'!C$18>0,'Supuestos'!C$18*'Supuestos'!$B$37*'Supuestos'!$B$25+'Supuestos'!$B$38*'Supuestos'!$B$25,0) | D12: =IF('Supuestos'!D$18>0,'Supuestos'!D$18*'Supuestos'!$B$37*'Supuestos'!$B$25+'Supuestos'!$B$38*'Supuestos'!$B$25,0) | E12: =IF('Supuestos'!B$18>0,'Supuestos'!B$18*'Supuestos'!$B$37*'Supuestos'!$B$25+'Supuestos'!$B$38*'Supuestos'!$B$25,0) | F12: =IF('Supuestos'!C$18>0,'Supuestos'!C$18*'Supuestos'!$B$37*'Supuestos'!$B$25+'Supuestos'!$B$38*'Supuestos'!$B$25,0) | G12: =IF('Supuestos'!D$18>0,'Supuestos'!D$18*'Supuestos'!$B$37*'Supuestos'!$B$25+'Supuestos'!$B$38*'Supuestos'!$B$25,0) | H12: €/mes
A13: COGS software | B13: =SUM(B6:B12) | C13: =SUM(C6:C12) | D13: =SUM(D6:D12) | E13: =SUM(E6:E12) | F13: =SUM(F6:F12) | G13: =SUM(G6:G12) | H13: €/mes
A14: Margen bruto software | B14: =(B5-B13)/B5 | C14: =(C5-C13)/C5 | D14: =(D5-D13)/D5 | E14: =(E5-E13)/E5 | F14: =(F5-F13)/F5 | G14: =(G5-G13)/G5 | H14: %
A15: Soporte humano | B15: ='Supuestos'!B$19/60*'Supuestos'!$B$39 | C15: ='Supuestos'!C$19/60*'Supuestos'!$B$39 | D15: ='Supuestos'!D$19/60*'Supuestos'!$B$39 | E15: ='Supuestos'!B$19/60*'Supuestos'!$B$39 | F15: ='Supuestos'!C$19/60*'Supuestos'!$B$39 | G15: ='Supuestos'!D$19/60*'Supuestos'!$B$39 | H15: €/mes
A16: Onboarding amortizado | B16: ='Supuestos'!B$20/60*'Supuestos'!$B$39/12 | C16: ='Supuestos'!C$20/60*'Supuestos'!$B$39/12 | D16: ='Supuestos'!D$20/60*'Supuestos'!$B$39/12 | E16: ='Supuestos'!B$20/60*'Supuestos'!$B$39/12 | F16: ='Supuestos'!C$20/60*'Supuestos'!$B$39/12 | G16: ='Supuestos'!D$20/60*'Supuestos'!$B$39/12 | H16: €/mes
A17: Fijo asignado | B17: ='Supuestos'!$B$40/'Supuestos'!$B$44 | C17: ='Supuestos'!$B$40/'Supuestos'!$B$44 | D17: ='Supuestos'!$B$40/'Supuestos'!$B$44 | E17: ='Supuestos'!$B$40/'Supuestos'!$B$44 | F17: ='Supuestos'!$B$40/'Supuestos'!$B$44 | G17: ='Supuestos'!$B$40/'Supuestos'!$B$44 | H17: €/mes
A18: Contribucion | B18: =B5-B13-B15-B16-B17 | C18: =C5-C13-C15-C16-C17 | D18: =D5-D13-D15-D16-D17 | E18: =E5-E13-E15-E16-E17 | F18: =F5-F13-F15-F16-F17 | G18: =G5-G13-G15-G16-G17 | H18: €/mes
A19: Margen de contribucion | B19: =B18/B5 | C19: =C18/C5 | D19: =D18/D5 | E19: =E18/E5 | F19: =F18/F5 | G19: =G18/G5 | H19: %
A20: Ingreso si el precio incluyera IVA | B20: =B5/(1+'Supuestos'!$B$43) | C20: =C5/(1+'Supuestos'!$B$43) | D20: =D5/(1+'Supuestos'!$B$43) | E20: =E5/(1+'Supuestos'!$B$43) | F20: =F5/(1+'Supuestos'!$B$43) | G20: =G5/(1+'Supuestos'!$B$43) | H20: €/mes
A21: Contribucion si incluyera IVA | B21: =B20-B13-B15-B16-B17 | C21: =C20-C13-C15-C16-C17 | D21: =D20-D13-D15-D16-D17 | E21: =E20-E13-E15-E16-E17 | F21: =F20-F13-F15-F16-F17 | G21: =G20-G13-G15-G16-G17 | H21: €/mes
A22: IA: 100% de creditos con Haiku | B22: ='Supuestos'!B$9*'Supuestos'!$B$31*'Supuestos'!$B$25 | C22: ='Supuestos'!C$9*'Supuestos'!$B$31*'Supuestos'!$B$25 | D22: ='Supuestos'!D$9*'Supuestos'!$B$31*'Supuestos'!$B$25 | E22: ='Supuestos'!B$9*'Supuestos'!$B$31*'Supuestos'!$B$25 | F22: ='Supuestos'!C$9*'Supuestos'!$B$31*'Supuestos'!$B$25 | G22: ='Supuestos'!D$9*'Supuestos'!$B$31*'Supuestos'!$B$25 | H22: €/mes
A23: Margen bruto en peor caso IA | B23: =(B5-(B13-B8+B22))/B5 | C23: =(C5-(C13-C8+C22))/C5 | D23: =(D5-(D13-D8+D22))/D5 | E23: =(E5-(E13-E8+E22))/E5 | F23: =(F5-(F13-F8+F22))/F5 | G23: =(G5-(G13-G8+G22))/G5 | H23: %

Sheet Hipotesis_Externa
A1: Hipotesis de coste del documento externo
A2: Reproduccion literal de la tabla recibida. Su propio encabezado la titula 'Calculo (Hipotesis)': no lleva fuente ni fecha, y aplica el mismo coste a todos los planes independientemente del uso.
A4: Tabla recibida
A5: Concepto de gasto | B5: Calculo (hipotesis) | C5: Coste mensual/usuario | F5: Contraste con el modelo Noesis
A6: API de Meta (WhatsApp) | B6: 150 mensajes enviados x 0,0166 € | C6: =150*Supuestos!B29 | F6: El modelo Noesis usa 30/80/200 mensajes segun plan, no 150 fijos
A7: Inteligencia Artificial (LLM) | B7: 150 procesamientos x ~0,02 € | C7: 3 | F7: El modelo Noesis estima 0,05/0,22/0,69 €: el cerebro interno resuelve el 60%
A8: Servidor y base de datos | B8: Prorrateo basico por usuario | C8: 1 | F8: El modelo Noesis reparte 65 € de plataforma entre las cuentas activas
A9: COSTE TOTAL VARIABLE | B9: Mensual por usuario | C9: =SUM(C6:C8)
A11: Margen resultante con esta hipotesis
A12: Plan | B12: Precio adoptado | C12: Coste variable | D12: Contribucion bruta | E12: Margen | F12: Nota
A13: Autonomo | B13: =Supuestos!B7 | C13: =$C$9 | D13: =B13-C13 | E13: =D13/B13 | F13: No descuenta soporte, onboarding ni fijo: no es comparable con la contribucion de Unit_Economics
A14: Negocio | B14: =Supuestos!C7 | C14: =$C$9 | D14: =B14-C14 | E14: =D14/B14 | F14: No descuenta soporte, onboarding ni fijo: no es comparable con la contribucion de Unit_Economics
A15: Premium | B15: =Supuestos!D7 | C15: =$C$9 | D15: =B15-C15 | E15: =D15/B15 | F15: No descuenta soporte, onboarding ni fijo: no es comparable con la contribucion de Unit_Economics

Sheet Comparador
A1: Comparador de escenarios de coste
A2: Que pasa con el margen si el coste real por usuario resulta ser el del documento externo en lugar del estimado internamente. Solo compara COGS variable, para que la base sea la misma.
A4: COGS software por plan
A5: Escenario | B5: Autonomo | C5: Negocio | D5: Premium
A6: Modelo Noesis (con fuentes) | B6: =Unit_Economics!E13 | C6: =Unit_Economics!F13 | D6: =Unit_Economics!G13
A7: Hipotesis externa | B7: =Hipotesis_Externa!$C$9 | C7: =Hipotesis_Externa!$C$9 | D7: =Hipotesis_Externa!$C$9
A8: Diferencia | B8: =B7-B6 | C8: =C7-C6 | D8: =D7-D6
A9: Multiplicador | B9: =IF(B6>0,B7/B6,"") | C9: =IF(C6>0,C7/C6,"") | D9: =IF(D6>0,D7/D6,"")
A11: Margen bruto comparado
A12: Escenario | B12: Autonomo | C12: Negocio | D12: Premium
A13: Modelo Noesis | B13: =Unit_Economics!E14 | C13: =Unit_Economics!F14 | D13: =Unit_Economics!G14
A14: Hipotesis externa | B14: =(Supuestos!B7-Hipotesis_Externa!$C$9)/Supuestos!B7 | C14: =(Supuestos!C7-Hipotesis_Externa!$C$9)/Supuestos!C7 | D14: =(Supuestos!D7-Hipotesis_Externa!$C$9)/Supuestos!D7
A15: Puntos perdidos | B15: =B13-B14 | C15: =C13-C14 | D15: =D13-D14
A17: Como leerlo
A18: La hipotesis externa aplica un coste plano por usuario, asi que penaliza mucho al plan barato y apenas al caro, mientras que el modelo Noesis escala el coste con el uso incluido en cada plan. Si el piloto midiera un consumo parecido al de la hipotesis, el plan Autonomo seria el primero en sufrir. Es el escenario que conviene vigilar durante los primeros 30 dias.

Sheet Anual_vs_Mensual
A1: Tarifa anual frente a mensual
A2: El anual cobra 11 meses y da acceso 12: un descuento real del 8,3%. Se eligio este nivel, y no dos meses gratis, para proteger el margen de Premium mientras el piloto no ha medido voz y soporte reales.
A4: Plan | B4: Mensual | C4: Cobro anual | D4: Equivalente/mes | E4: Ahorro/ano | F4: Contribucion mensual | G4: Margen contribucion
A5: Autonomo | B5: =Supuestos!B7 | C5: 319 | D5: =C5/12 | E5: =B5*12-C5 | F5: 18.69 | G5: =F5/D5
A6: Negocio | B6: =Supuestos!C7 | C6: 539 | D6: =C6/12 | E6: =B6*12-C6 | F6: 31.12 | G6: =F6/D6
A7: Premium | B7: =Supuestos!D7 | C7: 1089 | D7: =C7/12 | E7: =B7*12-C7 | F7: 49.12 | G7: =F7/D7
A9: La contribucion anual es una estimacion del analisis del 15/07/2026 con el mismo uso, soporte y onboarding del escenario base y una sola comision Stripe prorrateada. El anual mejora caja y reduce comisiones, pero obliga a reservar capacidad de servicio durante doce meses.

Sheet Escala_Breakeven
A1: Escala y punto de equilibrio
A2: Ingreso y resultado segun numero de cuentas, con el mix y el opex de la hoja Supuestos. El opex de 3.500 € es una hipotesis de planificacion, NO el gasto contable actual.
A4: Cuentas | B4: Ingreso mensual | C4: Contribucion total | D4: Opex fijo | E4: Resultado | F4: Margen sobre ingreso
A5: 10 | B5: =A5*(Supuestos!$B$7*Supuestos!$B$8+Supuestos!$C$7*Supuestos!$C$8+Supuestos!$D$7*Supuestos!$D$8) | C5: =A5*(Unit_Economics!$E$18*Supuestos!$B$8+Unit_Economics!$F$18*Supuestos!$C$8+Unit_Economics!$G$18*Supuestos!$D$8) | D5: =Supuestos!$B$41 | E5: =C5-D5 | F5: =IF(B5>0,E5/B5,"")
A6: 25 | B6: =A6*(Supuestos!$B$7*Supuestos!$B$8+Supuestos!$C$7*Supuestos!$C$8+Supuestos!$D$7*Supuestos!$D$8) | C6: =A6*(Unit_Economics!$E$18*Supuestos!$B$8+Unit_Economics!$F$18*Supuestos!$C$8+Unit_Economics!$G$18*Supuestos!$D$8) | D6: =Supuestos!$B$41 | E6: =C6-D6 | F6: =IF(B6>0,E6/B6,"")
A7: 50 | B7: =A7*(Supuestos!$B$7*Supuestos!$B$8+Supuestos!$C$7*Supuestos!$C$8+Supuestos!$D$7*Supuestos!$D$8) | C7: =A7*(Unit_Economics!$E$18*Supuestos!$B$8+Unit_Economics!$F$18*Supuestos!$C$8+Unit_Economics!$G$18*Supuestos!$D$8) | D7: =Supuestos!$B$41 | E7: =C7-D7 | F7: =IF(B7>0,E7/B7,"")
A8: 100 | B8: =A8*(Supuestos!$B$7*Supuestos!$B$8+Supuestos!$C$7*Supuestos!$C$8+Supuestos!$D$7*Supuestos!$D$8) | C8: =A8*(Unit_Economics!$E$18*Supuestos!$B$8+Unit_Economics!$F$18*Supuestos!$C$8+Unit_Economics!$G$18*Supuestos!$D$8) | D8: =Supuestos!$B$41 | E8: =C8-D8 | F8: =IF(B8>0,E8/B8,"")
A9: 120 | B9: =A9*(Supuestos!$B$7*Supuestos!$B$8+Supuestos!$C$7*Supuestos!$C$8+Supuestos!$D$7*Supuestos!$D$8) | C9: =A9*(Unit_Economics!$E$18*Supuestos!$B$8+Unit_Economics!$F$18*Supuestos!$C$8+Unit_Economics!$G$18*Supuestos!$D$8) | D9: =Supuestos!$B$41 | E9: =C9-D9 | F9: =IF(B9>0,E9/B9,"")
A10: 150 | B10: =A10*(Supuestos!$B$7*Supuestos!$B$8+Supuestos!$C$7*Supuestos!$C$8+Supuestos!$D$7*Supuestos!$D$8) | C10: =A10*(Unit_Economics!$E$18*Supuestos!$B$8+Unit_Economics!$F$18*Supuestos!$C$8+Unit_Economics!$G$18*Supuestos!$D$8) | D10: =Supuestos!$B$41 | E10: =C10-D10 | F10: =IF(B10>0,E10/B10,"")
A11: 200 | B11: =A11*(Supuestos!$B$7*Supuestos!$B$8+Supuestos!$C$7*Supuestos!$C$8+Supuestos!$D$7*Supuestos!$D$8) | C11: =A11*(Unit_Economics!$E$18*Supuestos!$B$8+Unit_Economics!$F$18*Supuestos!$C$8+Unit_Economics!$G$18*Supuestos!$D$8) | D11: =Supuestos!$B$41 | E11: =C11-D11 | F11: =IF(B11>0,E11/B11,"")
A12: 300 | B12: =A12*(Supuestos!$B$7*Supuestos!$B$8+Supuestos!$C$7*Supuestos!$C$8+Supuestos!$D$7*Supuestos!$D$8) | C12: =A12*(Unit_Economics!$E$18*Supuestos!$B$8+Unit_Economics!$F$18*Supuestos!$C$8+Unit_Economics!$G$18*Supuestos!$D$8) | D12: =Supuestos!$B$41 | E12: =C12-D12 | F12: =IF(B12>0,E12/B12,"")
A13: 500 | B13: =A13*(Supuestos!$B$7*Supuestos!$B$8+Supuestos!$C$7*Supuestos!$C$8+Supuestos!$D$7*Supuestos!$D$8) | C13: =A13*(Unit_Economics!$E$18*Supuestos!$B$8+Unit_Economics!$F$18*Supuestos!$C$8+Unit_Economics!$G$18*Supuestos!$D$8) | D13: =Supuestos!$B$41 | E13: =C13-D13 | F13: =IF(B13>0,E13/B13,"")
A14: 750 | B14: =A14*(Supuestos!$B$7*Supuestos!$B$8+Supuestos!$C$7*Supuestos!$C$8+Supuestos!$D$7*Supuestos!$D$8) | C14: =A14*(Unit_Economics!$E$18*Supuestos!$B$8+Unit_Economics!$F$18*Supuestos!$C$8+Unit_Economics!$G$18*Supuestos!$D$8) | D14: =Supuestos!$B$41 | E14: =C14-D14 | F14: =IF(B14>0,E14/B14,"")
A15: 1000 | B15: =A15*(Supuestos!$B$7*Supuestos!$B$8+Supuestos!$C$7*Supuestos!$C$8+Supuestos!$D$7*Supuestos!$D$8) | C15: =A15*(Unit_Economics!$E$18*Supuestos!$B$8+Unit_Economics!$F$18*Supuestos!$C$8+Unit_Economics!$G$18*Supuestos!$D$8) | D15: =Supuestos!$B$41 | E15: =C15-D15 | F15: =IF(B15>0,E15/B15,"")
A17: Punto de equilibrio exacto
A18: Cuentas necesarias | B18: =ROUNDUP(Supuestos!B41/(Unit_Economics!E18*Supuestos!B8+Unit_Economics!F18*Supuestos!C8+Unit_Economics!G18*Supuestos!D8),0) | C18: Con el catalogo adoptado y el mix 55/35/10. El analisis del 15/07/2026 lo situo en unas 120 cuentas.

Sheet Opciones_IA
A1: Coste de IA por opcion
A2: Con 8.000 tokens de entrada y 1.200 de salida por interaccion avanzada. Sirve para decidir cuando compensa alojar un modelo propio en lugar de pagar por uso.
A4: Opcion | B4: Coste/interaccion | C4: 75/mes | D4: 300/mes | E4: 1.500/mes | F4: Nota
A5: Cerebro determinista Noesis | B5: 0 | C5: 0 | D5: 0 | E5: 0 | F5: Codigo propio: sin coste por token
A6: Cloudflare Qwen3 30B A3B | B6: 0.0007 | C6: 0.05 | D6: 0.21 | E6: 1.07 | F6: Proveedor compatible barato
A7: Groq Qwen3 32B | B7: 0.0027 | C7: 0.2 | D7: 0.8 | E7: 3.98 | F7: Latencia baja
A8: Anthropic Haiku 4.5 | B8: 0.0123 | C8: 0.92 | D8: 3.68 | E8: 18.41 | F8: Respaldo de calidad
A10: Cuando compensa alojar un modelo propio
A11: GPU 16 GB a 0,58 USD/h, 730 h/mes | B11: 423,40 USD (~371 € al cambio usado)
A12: Cruce frente a Haiku 4.5 | B12: ~30.243 interacciones/mes
A13: Cruce frente a Groq Qwen3 | B13: ~139.828 interacciones/mes
A14: Conclusion | B14: Por debajo de ese volumen, cerebro interno + pago por uso es mas barato y exige menos operacion
A16: No existe un servidor publico gratuito adecuado como nucleo de produccion: los tiers gratis pueden cambiar, limitar concurrencia, cortar solicitudes y tratar datos fuera de Noesis. El modelo open source evita licencia por token, pero no elimina computo, seguridad ni mantenimiento.

Sheet Datos_Pendientes
A1: Datos que faltan — rellenar antes de usar este modelo
A2: Estas cifras NO constan en el repositorio y NO se han estimado. Mientras esten vacias, el modelo es un escenario de planificacion y no un reflejo de la empresa. Rellenar la columna Valor real.
A4: Concepto | B4: Valor real | C4: Unidad | D4: Quien lo tiene | E4: Por que hace falta
A5: Forma juridica y NIF | C5: texto | D5: Founder | E5: Determina IRPF/IS, cuota de autonomos y la verificacion de Meta
A6: Reparto societario entre socios | C6: % | D6: Founder y socio | E6: Sin el no se puede repartir resultado ni valorar
A7: Sueldo o retirada mensual founder | C7: €/mes | D7: Founder | E7: Es la mayor partida del opex real; ahora es hipotesis
A8: Sueldo o retirada mensual socio | C8: €/mes | D8: Socio | E8: Idem
A9: Cuota de autonomos por socio | C9: €/mes | D9: Gestoria | E9: Coste fijo mensual ineludible
A10: Gestoria / asesoria | C10: €/mes | D10: Gestoria | E10: Fijo recurrente
A11: Factura real de Railway | C11: €/mes | D11: Founder | E11: Sustituye el prorrateo de plataforma de 65 €
A12: Dominio y correo | C12: €/ano | D12: Founder | E12: Fijo menor pero real
A13: Herramientas y suscripciones | C13: €/mes | D13: Founder | E13: IDE, diseno, analitica, almacenamiento
A14: Seguro de responsabilidad civil | C14: €/ano | D14: Founder | E14: Habitual antes de operar con datos de terceros
A15: Capital aportado a fecha de hoy | C15: € | D15: Founder y socio | E15: El vault cita ~4.000 € iniciales; confirmar
A16: Ingresos facturados hasta hoy | C16: € | D16: Founder | E16: Si es 0, el modelo es prospectivo y debe decirlo
... A20: Presupuesto de marketing | C20: €/mes | D20: Founder | E20: Entra en el opex y condiciona el crecimiento

Sheet Fuentes
A1: Fuentes y cautelas
A2: Tarifas consultadas el 15/07/2026. Pueden haber cambiado: verificar antes de tomar una decision de precio o de proveedor.
A4: Driver | B4: Proveedor | C4: URL | D4: Consultado
A5: Comisiones de pago | B5: Stripe Espana | C5: https://stripe.com/es/pricing | D5: 15/07/2026
A6: Coste de modelo de respaldo | B6: Anthropic Haiku | C6: https://www.anthropic.com/claude/haiku | D6: 15/07/2026
A7: Plataforma y almacenamiento | B7: Railway | C7: https://docs.railway.com/pricing | D7: 15/07/2026
A8: Correo transaccional | B8: Resend | C8: https://resend.com/docs/knowledge-base/what-is-resend-pricing | D8: 15/07/2026
A9: Mensajeria utility | B9: WhatsApp Business | C9: https://whatsappbusiness.com/products/platform-pricing/ | D9: 15/07/2026
A10: Tipo de cambio | B10: ECB | C10: https://www.ecb.europa.eu/stats/policy_and_exchange_rates/euro_reference_exchange_rates/html/index.en.html | D10: 14/07/2026
A11: Voz telefonica | B11: Retell | C11: https://www.retellai.com/pricing | D11: 15/07/2026
A12: Transcripcion | B12: Groq Speech-to-Text | C12: https://console.groq.com/docs/speech-to-text | D12: 15/07/2026
A13: GPU serverless | B13: Runpod | C13: https://www.runpod.io/product/serverless | D13: 15/07/2026
A14: Modelo abierto | B14: Qwen3 | C14: https://github.com/QwenLM/Qwen3 | D14: 15/07/2026
A17: Cautelas
A18: La tarifa utility de WhatsApp en Espana usa ademas una rate card publicada por un tercero, porque la tabla oficial dinamica no expuso el valor durante la consulta. Las tarifas pueden cambiar y no siempre incluyen impuestos. El coste de la hoja Hipotesis_Externa no tiene fuente ni fecha conocidas.
